posit/__init__.py
posit/_version.py
posit/connect/README.md
posit/connect/__init__.py
posit/connect/_utils.py
posit/connect/auth.py
posit/connect/bundles.py
posit/connect/client.py
posit/connect/config.py
posit/connect/content.py
posit/connect/context.py
posit/connect/cursors.py
posit/connect/env.py
posit/connect/environments.py
posit/connect/errors.py
posit/connect/groups.py
posit/connect/hooks.py
posit/connect/jobs.py
posit/connect/me.py
posit/connect/packages.py
posit/connect/paginator.py
posit/connect/permissions.py
posit/connect/repository.py
posit/connect/resources.py
posit/connect/sessions.py
posit/connect/system.py
posit/connect/tags.py
posit/connect/tasks.py
posit/connect/urls.py
posit/connect/users.py
posit/connect/vanities.py
posit/connect/variants.py
posit/connect/external/__init__.py
posit/connect/external/aws.py
posit/connect/external/databricks.py
posit/connect/external/snowflake.py
posit/connect/metrics/__init__.py
posit/connect/metrics/hits.py
posit/connect/metrics/metrics.py
posit/connect/metrics/rename_params.py
posit/connect/metrics/shiny_usage.py
posit/connect/metrics/usage.py
posit/connect/metrics/visits.py
posit/connect/oauth/__init__.py
posit/connect/oauth/associations.py
posit/connect/oauth/integrations.py
posit/connect/oauth/oauth.py
posit/connect/oauth/sessions.py
posit/connect/oauth/types.py
posit/workbench/__init__.py
posit/workbench/client.py
posit/workbench/context.py
posit/workbench/resources.py
posit/workbench/urls.py
posit/workbench/auth/__init__.py
posit/workbench/auth/auth.py
posit/workbench/auth/cookie_reader.py
posit/workbench/external/__init__.py
posit/workbench/external/databricks.py
posit/workbench/oauth/__init__.py
posit/workbench/oauth/integrations.py
posit/workbench/oauth/oauth.py
posit_sdk-0.15.1.dist-info/licenses/LICENSE
posit_sdk-0.15.1.dist-info/METADATA
posit_sdk-0.15.1.dist-info/WHEEL
posit_sdk-0.15.1.dist-info/top_level.txt
posit_sdk-0.15.1.dist-info/RECORD
