Metadata-Version: 2.4
Name: posit-sdk
Version: 0.15.1
Summary: Posit SDK for Python
License: MIT License
Project-URL: Source, https://github.com/posit-dev/posit-sdk-py
Project-URL: Issues, https://github.com/posit-dev/posit-sdk-py/issues
Keywords: posit,sdk
Classifier: Development Status :: 5 - Production/Stable
Classifier: Intended Audience :: Developers
Classifier: License :: OSI Approved :: MIT License
Classifier: Operating System :: OS Independent
Classifier: Programming Language :: Python :: 3
Classifier: Topic :: Software Development :: Libraries
Classifier: Typing :: Typed
Requires-Python: >=3.8
License-File: LICENSE
Requires-Dist: requests<3,>=2.31.0
Requires-Dist: packaging
Requires-Dist: typing-extensions
Dynamic: license-file
